[
  {
    "date": "Idag",
    "links": [
      {
        "title": "The Private Chef For Korea's #1 Gaming Team",
        "icon": "Film",
        "type": "youtube",
        "src": "D2l2MsTAvLo",
        "comment_url": "?p=komment\u0026id=267708",
        "comment_number": "0",
        "nsfw": false
      },
      {
        "title": "Ni män kanske inte är ensamma i era tankar?",
        "icon": "Film",
        "type": "youtube",
        "src": "740EcJLzsY8",
        "comment_url": "?p=komment\u0026id=267707",
        "comment_number": "0",
        "nsfw": false
      },
      {
        "title": "Kille förklarar inflationen de fem senaste åren",
        "icon": "Film",
        "type": "redirect",
        "src": "https://youtube.com/shorts/HdXPScgs7ck?si=uHS70HzSG52NukGW",
        "comment_url": "?p=komment\u0026id=267706",
        "comment_number": "0",
        "nsfw": false
      },
      {
        "title": "Ryska Sankt Petersburg attackerat",
        "icon": "Film",
        "type": "iframe",
        "src": "https://www.itemfix.com/v?t=am0t0f",
        "comment_url": "?p=komment\u0026id=267704",
        "comment_number": "1",
        "nsfw": false
      },
      {
        "title": "Fallet Hammarskjöld @ SVT Play",
        "icon": "Hemsida",
        "type": "redirect",
        "src": "https://www.svtplay.se/video/KPvBZgX/fallet-hammarskjold/avsnitt-1",
        "comment_url": "?p=komment\u0026id=267703",
        "comment_number": "0",
        "nsfw": false
      }
    ]
  }
]
